pydantic_autocli/__init__.py
pydantic_autocli/cli.py
pydantic_autocli-0.2.1.dist-info/METADATA
pydantic_autocli-0.2.1.dist-info/WHEEL
pydantic_autocli-0.2.1.dist-info/licenses/LICENSE
pydantic_autocli-0.2.1.dist-info/RECORD
