Metadata-Version: 2.4
Name: pydantic-autocli
Version: 0.2.1
Summary: Automatically generate CLI from Pydantic models
Project-URL: Homepage, https://github.com/endaaman/pydantic-autocli
Author-email: Ken Enda <ken@endaaman.com>
License: MIT License
License-File: LICENSE
Requires-Python: >=3.9
Requires-Dist: pydantic<2.12
Provides-Extra: dev
Requires-Dist: pytest-cov>=6.0.0; extra == 'dev'
Requires-Dist: pytest>=7.4.4; extra == 'dev'
Requires-Dist: taskipy>=1.14.1; extra == 'dev'
